gepa/__init__.py
gepa/api.py
gepa/gepa_utils.py
gepa/py.typed
gepa/adapters/__init__.py
gepa/adapters/anymaths_adapter/__init__.py
gepa/adapters/anymaths_adapter/anymaths_adapter.py
gepa/adapters/default_adapter/__init__.py
gepa/adapters/default_adapter/default_adapter.py
gepa/adapters/dspy_adapter/__init__.py
gepa/adapters/dspy_adapter/dspy_adapter.py
gepa/adapters/dspy_full_program_adapter/dspy_program_proposal_signature.py
gepa/adapters/dspy_full_program_adapter/full_program_adapter.py
gepa/adapters/generic_rag_adapter/__init__.py
gepa/adapters/generic_rag_adapter/evaluation_metrics.py
gepa/adapters/generic_rag_adapter/generic_rag_adapter.py
gepa/adapters/generic_rag_adapter/rag_pipeline.py
gepa/adapters/generic_rag_adapter/vector_store_interface.py
gepa/adapters/generic_rag_adapter/vector_stores/__init__.py
gepa/adapters/generic_rag_adapter/vector_stores/chroma_store.py
gepa/adapters/generic_rag_adapter/vector_stores/lancedb_store.py
gepa/adapters/generic_rag_adapter/vector_stores/milvus_store.py
gepa/adapters/generic_rag_adapter/vector_stores/qdrant_store.py
gepa/adapters/generic_rag_adapter/vector_stores/weaviate_store.py
gepa/adapters/mcp_adapter/__init__.py
gepa/adapters/mcp_adapter/mcp_adapter.py
gepa/adapters/mcp_adapter/mcp_client.py
gepa/adapters/terminal_bench_adapter/__init__.py
gepa/adapters/terminal_bench_adapter/terminal_bench_adapter.py
gepa/core/__init__.py
gepa/core/adapter.py
gepa/core/data_loader.py
gepa/core/engine.py
gepa/core/result.py
gepa/core/state.py
gepa/examples/__init__.py
gepa/examples/aime.py
gepa/examples/anymaths-bench/eval_default.py
gepa/examples/anymaths-bench/train_anymaths.py
gepa/examples/mcp_adapter/__init__.py
gepa/examples/mcp_adapter/mcp_optimization_example.py
gepa/examples/rag_adapter/__init__.py
gepa/examples/rag_adapter/rag_optimization.py
gepa/examples/terminal-bench/train_terminus.py
gepa/logging/__init__.py
gepa/logging/experiment_tracker.py
gepa/logging/logger.py
gepa/logging/utils.py
gepa/proposer/__init__.py
gepa-0.0.23.dist-info/licenses/LICENSE
gepa-0.0.23.dist-info/METADATA
gepa-0.0.23.dist-info/WHEEL
gepa-0.0.23.dist-info/top_level.txt
gepa-0.0.23.dist-info/RECORD
