Metadata-Version: 2.4
Name: gepa
Version: 0.0.23
Summary: A framework for optimizing textual system components (AI prompts, code snippets, etc.) using LLM-based reflection and Pareto-efficient evolutionary search.
Author-email: Lakshya A Agrawal <lakshyaaagrawal@berkeley.edu>
License: MIT
Project-URL: Homepage, https://github.com/gepa-ai/gepa
Project-URL: Bug Tracker, https://github.com/gepa-ai/gepa/issues
Requires-Python: <3.14,>=3.10
License-File: LICENSE
Provides-Extra: full
Requires-Dist: litellm>=1.64.0; extra == "full"
Requires-Dist: datasets>=2.14.6; extra == "full"
Requires-Dist: mlflow>=3.0.0; extra == "full"
Requires-Dist: wandb; extra == "full"
Requires-Dist: tqdm>=4.66.1; extra == "full"
Provides-Extra: dspy
Provides-Extra: test
Requires-Dist: gepa[full]; extra == "test"
Requires-Dist: pytest; extra == "test"
Requires-Dist: pyright; extra == "test"
Provides-Extra: build
Requires-Dist: setuptools>=77.0.1; extra == "build"
Requires-Dist: wheel; extra == "build"
Requires-Dist: build; extra == "build"
Requires-Dist: twine; extra == "build"
Requires-Dist: semver; extra == "build"
Requires-Dist: packaging; extra == "build"
Requires-Dist: requests; extra == "build"
Provides-Extra: dev
Requires-Dist: gepa[test]; extra == "dev"
Requires-Dist: gepa[build]; extra == "dev"
Requires-Dist: pre-commit; extra == "dev"
Requires-Dist: build>=1.0.3; extra == "dev"
Requires-Dist: ruff>=0.3.0; extra == "dev"
Dynamic: license-file
